gbx/lzo.cpython-313-darwin.so
gbx_py-0.3.0.dist-info/RECORD
gbx_py-0.3.0.dist-info/WHEEL
gbx_py-0.3.0.dist-info/top_level.txt
gbx_py-0.3.0.dist-info/METADATA
gbx_py-0.3.0.dist-info/licenses/LICENSE
