Metadata-Version: 2.4
Name: gbx-py
Version: 0.3.0
Summary: Read and write GBX files for Trackmania.
Home-page: https://github.com/schadocalex/gbx-py
Author: schadocalex
Author-email: Alexis Schad <schad.alexis@gmail.com>
Maintainer: schadocalex
Maintainer-email: Alexis Schad <schad.alexis@gmail.com>
License-Expression: MIT
Project-URL: bugs, https://github.com/schadocalex/gbx-py/issues
Project-URL: changelog, https://github.com/schadocalex/gbx-py/blob/master/changelog.md
Project-URL: homepage, https://github.com/schadocalex/gbx-py
Requires-Python: >=3.10
License-File: LICENSE
Provides-Extra: test
Requires-Dist: coverage; extra == "test"
Requires-Dist: pytest; extra == "test"
Requires-Dist: ruff; extra == "test"
Requires-Dist: ty; extra == "test"
Requires-Dist: ipdb; extra == "test"
Dynamic: author
Dynamic: home-page
Dynamic: license-file
Dynamic: maintainer
Dynamic: requires-python
